jsparser/__init__.py
jsparser/jsparserdata.py
jsparser/parser.py
jsparser/std_nodes.py
jsparser-2.7.3.dist-info/METADATA
jsparser-2.7.3.dist-info/WHEEL
jsparser-2.7.3.dist-info/top_level.txt
jsparser-2.7.3.dist-info/RECORD
